pytesy/__init__.py
pyTesy-0.0.3.dist-info/LICENSE
pyTesy-0.0.3.dist-info/METADATA
pyTesy-0.0.3.dist-info/WHEEL
pyTesy-0.0.3.dist-info/top_level.txt
pyTesy-0.0.3.dist-info/RECORD
