Metadata-Version: 2.1
Name: pyTesy
Version: 0.0.3
Summary: Library for Tesy smart home devices
Home-page: https://github.com/StyraHem/pyTesy
Author: StyraHem / Tarra AB
Author-email: info@styrahem.se
License: UNKNOWN
Platform: UNKNOWN
Classifier: Programming Language :: Python :: 2.7
Classifier: Programming Language :: Python :: 3
Classifier: License :: OSI Approved :: MIT License
Classifier: Operating System :: OS Independent
